03_FSM/03_01_detect_sequence_using_fsm/03_01_detect_sequence_using_fsm.sv
//----------------------------------------------------------------------------
// Example
//----------------------------------------------------------------------------

module detect_4_bit_sequence_using_fsm
(
  input  clk,
  input  rst,
  input  a,
  output detected
);

  // Detection of the "1010" sequence

  // States (F — First, S — Second)
  enum logic[2:0]
  {
     IDLE = 3'b000,
     F1   = 3'b001,
     F0   = 3'b010,
     S1   = 3'b011,
     S0   = 3'b100
  }
  state, new_state;

  // State transition logic
  always_comb
  begin
    new_state = state;

    // This lint warning is bogus because we assign the default value above
    // verilator lint_off CASEINCOMPLETE

    case (state)
      IDLE: if (  a) new_state = F1;
      F1:   if (~ a) new_state = F0;
      F0:   if (  a) new_state = S1;
            else     new_state = IDLE;
      S1:   if (~ a) new_state = S0;
            else     new_state = F1;
      S0:   if (  a) new_state = S1;
            else     new_state = IDLE;
    endcase

    // verilator lint_on CASEINCOMPLETE

  end

  // Output logic (depends only on the current state)
  assign detected = (state == S0);

  // State update
  always_ff @ (posedge clk)
    if (rst)
      state <= IDLE;
    else
      state <= new_state;
endmodule

//----------------------------------------------------------------------------
// Task
//----------------------------------------------------------------------------

module detect_6_bit_sequence_using_fsm
(
  input  clk,
  input  rst,
  input  a,
  output detected
);

  // Task:
  // Implement a module that detects the "110011" input sequence
  //
  // Hint: See Lecture 3 for details
  
    //States (number of passed)
  enum logic[2:0]
  {
    RESTART = 3'b000,
    S1      = 3'b001,
    S2      = 3'b010,
    S3      = 3'b011,
    S4      = 3'b100,
    S5      = 3'b101,
    S6      = 3'b110
  }
  state, new_state;

    //State transition logic
  always_comb
  begin
    new_state = state;

    case (state)
      RESTART: if ( a) new_state = S1;
      S1:      if ( a) new_state = S2;
               else    new_state = RESTART;
      S2:      if (~a) new_state = S3;
               else    new_state = S2;
      S3:      if (~a) new_state = S4;
               else    new_state = S1;
      S4:      if ( a) new_state = S5;
               else    new_state = RESTART;
      S5:      if ( a) new_state = S6;
               else    new_state = RESTART;
      S6:      if ( a) new_state = S2;
               else    new_state = S3;
    endcase
  end

    // State update
  always_ff @ (posedge clk)
    if (rst)
      state <= RESTART;
    else
      state <= new_state;

    // Output
  assign detected = (state == S6);

  endmodule

03_FSM/03_01_detect_sequence_using_fsm/testbench.sv
module testbench;

  logic clk;

  initial
  begin
    clk = '0;

    forever
      # 500 clk = ~ clk;
  end

  logic rst;

  initial
  begin
    rst <= 'x;
    repeat (2) @ (posedge clk);
    rst <= '1;
    repeat (2) @ (posedge clk);
    rst <= '0;
  end

  logic a, det4bit, det6bit;
  detect_4_bit_sequence_using_fsm det4b (.detected (det4bit),  .*);
  detect_6_bit_sequence_using_fsm det6b (.detected (det6bit), .*);

  localparam n = 24;

  // Ascending bit range in a packed vector is intentional here
  // verilator lint_off ASCRANGE

  // The sequence of input values
  localparam [0 : n - 1] seq_a       = 24'b0011_0101_1001_1001_1010_1000;

  // The sequence of expected output values
  localparam [0 : n - 1] seq_det4bit = 24'b0000_0001_0000_0000_0000_1010;
  localparam [0 : n - 1] seq_det6bit = 24'b0000_0000_0000_0100_0100_0000;

  // verilator lint_on ASCRANGE

  initial
  begin
    `ifdef __ICARUS__
        // Uncomment the following lines
        // to generate a VCD file and analyze it using GTKwave

         $dumpvars;
    `endif

    @ (negedge rst);

    for (int i = 0; i < n; i ++)
    begin
      a <= seq_a [i];

      @ (posedge clk);

      $display ("%b %b (%b) %b (%b)",
        a,
        det4bit, seq_det4bit[i],
        det6bit, seq_det6bit[i]);

      if (   det4bit !== seq_det4bit[i]
          || det6bit !== seq_det6bit[i])
      begin
        $display ("FAIL %s - see log above", `__FILE__, $time);
        $finish;
      end
    end

    $display ("PASS %s", `__FILE__);
    $finish;
  end

endmodule

03_FSM/03_01_detect_sequence_using_fsm/dump.vcd
$date
	Mon Jun 30 00:06:31 2025
$end
$version
	Icarus Verilog
$end
$timescale
	1s
$end
$scope module testbench $end
$var wire 1 ! det6bit $end
$var wire 1 " det4bit $end
$var parameter 32 # n $end
$var parameter 24 $ seq_a $end
$var parameter 24 % seq_det4bit $end
$var parameter 24 & seq_det6bit $end
$var reg 1 ' a $end
$var reg 1 ( clk $end
$var reg 1 ) rst $end
$scope module det4b $end
$var wire 1 ' a $end
$var wire 1 ( clk $end
$var wire 1 ) rst $end
$var wire 1 " detected $end
$var reg 3 * new_state [2:0] $end
$var reg 3 + state [2:0] $end
$upscope $end
$scope module det6b $end
$var wire 1 ' a $end
$var wire 1 ( clk $end
$var wire 1 ) rst $end
$var wire 1 ! detected $end
$var reg 3 , new_state [2:0] $end
$var reg 3 - state [2:0] $end
$upscope $end
$scope begin $ivl_for_loop0 $end
$var integer 32 . i [31:0] $end
$upscope $end
$upscope $end
$enddefinitions $end
$comment Show the parameter values. $end
$dumpall
b10001000000 &
b10000000000001010 %
b1101011001100110101000 $
b11000 #
$end
#0
$dumpvars
b0 .
bx -
bx ,
bx +
bx *
x)
0(
x'
x"
x!
$end
#500
1(
#1000
0(
#1500
1)
1(
#2000
0(
#2500
b0 *
b0 ,
0"
b0 +
0!
b0 -
1(
#3000
0(
#3500
0'
0)
1(
#4000
0(
#4500
b1 .
1(
#5000
0(
#5500
b1 *
b1 ,
1'
b10 .
1(
#6000
0(
#6500
b10 ,
b1 +
b1 -
b11 .
1(
#7000
0(
#7500
b10 *
b11 ,
0'
b10 -
b100 .
1(
#8000
0(
#8500
b11 *
b1 ,
b10 +
b11 -
1'
b101 .
1(
#9000
0(
#9500
b0 ,
b100 *
0'
b1 -
b11 +
b110 .
1(
#10000
0(
#10500
b11 *
b1 ,
1"
b100 +
b0 -
1'
b111 .
1(
#11000
0(
#11500
b10 ,
b1 *
b1 -
0"
b11 +
b1000 .
1(
#12000
0(
#12500
b10 *
b11 ,
b1 +
b10 -
0'
b1001 .
1(
#13000
0(
#13500
b100 ,
b0 *
b11 -
b10 +
b1010 .
1(
#14000
0(
#14500
b1 *
b101 ,
b0 +
b100 -
1'
b1011 .
1(
#15000
0(
#15500
b110 ,
b101 -
b1 +
b1100 .
1(
#16000
0(
#16500
b10 *
b11 ,
1!
b110 -
0'
b1101 .
1(
#17000
0(
#17500
b100 ,
b0 *
0!
b11 -
b10 +
b1110 .
1(
#18000
0(
#18500
b1 *
b101 ,
b0 +
b100 -
1'
b1111 .
1(
#19000
0(
#19500
b110 ,
b101 -
b1 +
b10000 .
1(
#20000
0(
#20500
b10 *
b11 ,
1!
b110 -
0'
b10001 .
1(
#21000
0(
#21500
b1 ,
b11 *
1'
0!
b11 -
b10 +
b10010 .
1(
#22000
0(
#22500
b100 *
b0 ,
b11 +
b1 -
0'
b10011 .
1(
#23000
0(
#23500
b1 ,
b11 *
1'
b0 -
1"
b100 +
b10100 .
1(
#24000
0(
#24500
b100 *
b0 ,
0"
b11 +
b1 -
0'
b10101 .
1(
#25000
0(
#25500
b0 *
b0 -
1"
b100 +
b10110 .
1(
#26000
0(
#26500
0"
b0 +
b10111 .
1(
#27000
0(
#27500
b11000 .
1(
